k8slibsonnet
