Metadata-Version: 2.1
Name: sentry-k8s-libsonnet
Version: 0.0.4
Summary: k8s-libsonnet repackaged as a python package
Classifier: Programming Language :: Python :: 3
Classifier: License :: OSI Approved :: Apache Software License
Classifier: Operating System :: OS Independent
License-File: LICENSE
